aiida_flexpart/__init__.py
aiida_flexpart/helpers.py
aiida_flexpart/utils.py
aiida_flexpart/calculations/__init__.py
aiida_flexpart/calculations/collect_sens.py
aiida_flexpart/calculations/flexpart_cosmo.py
aiida_flexpart/calculations/flexpart_ifs.py
aiida_flexpart/calculations/flexpart_post.py
aiida_flexpart/calculations/inversion.py
aiida_flexpart/data/__init__.py
aiida_flexpart/data/nc_data.py
aiida_flexpart/parsers/__init__.py
aiida_flexpart/parsers/flexpart_cosmo.py
aiida_flexpart/parsers/flexpart_ifs.py
aiida_flexpart/parsers/flexpart_post.py
aiida_flexpart/parsers/inversion.py
aiida_flexpart/templates/AGECLASSES.j2
aiida_flexpart/templates/COMMAND.j2
aiida_flexpart/templates/COMMAND_ifs.j2
aiida_flexpart/templates/OUTGRID.j2
aiida_flexpart/templates/OUTGRID_NEST.j2
aiida_flexpart/templates/OUTGRID_NEST_ifs.j2
aiida_flexpart/templates/OUTGRID_ifs.j2
aiida_flexpart/templates/RELEASES.j2
aiida_flexpart/templates/__init__.py
aiida_flexpart/templates/params.yaml
aiida_flexpart/workflows/__init__.py
aiida_flexpart/workflows/child_meteo_workflow.py
aiida_flexpart/workflows/child_sim_workflow.py
aiida_flexpart/workflows/inspect.py
aiida_flexpart/workflows/inversion_workflow.py
aiida_flexpart/workflows/multi_dates_workflow.py
aiida_flexpart/workflows/parent_workflow.py
aiida_flexpart-0.2.1.dist-info/entry_points.txt
aiida_flexpart-0.2.1.dist-info/LICENSE
aiida_flexpart-0.2.1.dist-info/WHEEL
aiida_flexpart-0.2.1.dist-info/METADATA
aiida_flexpart-0.2.1.dist-info/RECORD
