Metadata-Version: 2.1
Name: aiida-flexpart
Version: 0.2.1
Summary: AiiDA plugin for the FLEXPART code (simulation of atmospheric transport processes).
Author: 
Requires-Python: >=3.8
Classifier: Intended Audience :: Science/Research
Classifier: License :: OSI Approved :: MIT License
Classifier: Natural Language :: English
Classifier: Framework :: AiiDA
Classifier: Development Status :: 3 - Alpha
Classifier: Topic :: Scientific/Engineering :: Atmospheric Science
Classifier: Programming Language :: Python :: 3
Requires-Dist: aiida-core>=1.6.5,<3.0.0
Requires-Dist: six
Requires-Dist: psycopg2-binary<2.9
Requires-Dist: voluptuous
Requires-Dist: jinja2
Requires-Dist: netCDF4
Requires-Dist: pgtest~=1.3.1 ; extra == "dev"
Requires-Dist: pytest~=6.0 ; extra == "dev"
Requires-Dist: pytest-cov ; extra == "dev"
Requires-Dist: pre-commit~=2.2 ; extra == "dev"
Requires-Dist: sphinx ; extra == "docs"
Requires-Dist: sphinxcontrib-contentui ; extra == "docs"
Requires-Dist: sphinxcontrib-details-directive ; extra == "docs"
Requires-Dist: sphinx-rtd-theme ; extra == "docs"
Project-URL: Homepage, https://github.com/aiidaplugins/aiida-flexpart
Provides-Extra: dev
Provides-Extra: docs
